tomer/.DS_Store
tomer/__init__.py
tomer/resreg.py
tomer/tomer.py
tomer/data/.DS_Store
tomer/data/sequence_ogt_topt.csv
tomer-1.0.dist-info/METADATA
tomer-1.0.dist-info/RECORD
tomer-1.0.dist-info/WHEEL
tomer-1.0.dist-info/top_level.txt
