Metadata-Version: 2.1
Name: tomer
Version: 1.0
Summary: Predicting enzyme catalytic optimum temperature with ML
Home-page: https://github.com/jafetgado/tomer
Author: Japheth Gado
Author-email: japhethgado@gmail.com
License: GNU GPLv3
Keywords: machine-learning enzymes thermostability
Platform: UNKNOWN
Classifier: Programming Language :: Python :: 3
Classifier: Operating System :: OS Independent
Classifier: Topic :: Scientific/Engineering
Requires-Python: >=3
Requires-Dist: numpy
Requires-Dist: pandas
Requires-Dist: scipy
Requires-Dist: scikit-learn
